rtt/__init__.py
rtt-0.5.0.dist-info/entry_points.txt
rtt-0.5.0.dist-info/WHEEL
rtt-0.5.0.dist-info/METADATA
rtt-0.5.0.dist-info/RECORD
